{
    "files": {
        "OFT.Okx.dll": {
            "version": "2026-03-26",
            "md5": "2377e7ffc7a50992faf7f33bb41dc95a",
            "force_update": true,
            "update_id": "8edc97353dde3311"
        },
        "qidongqi.exe": {
            "version": "2026-03-28",
            "md5": "134bc397657def597b8e3efddc4ecd6f",
            "force_update": true,
            "update_id": "bd9025ca36aa5de0"
        },
        "ATAS_Ultra.exe": {
            "version": "2026-03-26",
            "md5": "b9b2f1dee4813abb8733d767822de04c",
            "force_update": true,
            "update_id": "be41760bbe58629b"
        },
        "ATASPlatform.exe": {
            "version": "2026-03-26",
            "md5": "7f542666480efc717632de144f8376c4",
            "force_update": true,
            "update_id": "a8a9cfa291fc8d30"
        }
    },
    "force_delete_k": false,
    "disabled": false,
    "message": "",
    "proxies": "https://ghproxy.cc/https://raw.githubusercontent.com,https://gh-proxy.com/https://raw.githubusercontent.com,https://raw.githubusercontent.com,https://ghfast.top/https://raw.githubusercontent.com,https://ghproxy.net/https://raw.githubusercontent.com"
}