{
    "dll_version": "1.0.0",
    "dll_md5": "",
    "force_update_dll": false,
    "launcher_version": "1.0.0",
    "launcher_md5": "",
    "force_update_launcher": false,
    "ultra_version": "2026-03-09",
    "ultra_md5": "4820755ce1769f9b44638fbdc0c7d1d7",
    "force_update_ultra": true,
    "force_delete_k": false,
    "disabled": false,
    "message": "",
    "proxies": "https://gh-proxy.com/https://raw.githubusercontent.com,https://ghproxy.cc/https://raw.githubusercontent.com,https://raw.githubusercontent.com,https://ghfast.top/https://raw.githubusercontent.com,https://ghproxy.net/https://raw.githubusercontent.com",
    "ultra_update_id": "92e66fab650d501d",
    "run_unbind": true
}